README.txt
setup.py
collective/__init__.py
collective.dexteritydiff.egg-info/PKG-INFO
collective.dexteritydiff.egg-info/SOURCES.txt
collective.dexteritydiff.egg-info/dependency_links.txt
collective.dexteritydiff.egg-info/entry_points.txt
collective.dexteritydiff.egg-info/namespace_packages.txt
collective.dexteritydiff.egg-info/not-zip-safe
collective.dexteritydiff.egg-info/requires.txt
collective.dexteritydiff.egg-info/top_level.txt
collective/dexteritydiff/README.txt
collective/dexteritydiff/__init__.py
collective/dexteritydiff/astextdiff.py
collective/dexteritydiff/binarydiff.py
collective/dexteritydiff/booldiff.py
collective/dexteritydiff/choicediff.py
collective/dexteritydiff/compounddiff.py
collective/dexteritydiff/config.py
collective/dexteritydiff/configure.zcml
collective/dexteritydiff/filefields.py
collective/dexteritydiff/filelistdiff.py
collective/dexteritydiff/i18n.py
collective/dexteritydiff/testing.py
collective/dexteritydiff/utils.py
collective/dexteritydiff/locales/pt_BR/LC_MESSAGES/collective.dexteritydiff.po
collective/dexteritydiff/tests/__init__.py
collective/dexteritydiff/tests/test_astextdiff.py
collective/dexteritydiff/tests/test_binarydiff.py
collective/dexteritydiff/tests/test_booldiff.py
collective/dexteritydiff/tests/test_choicediff.py
collective/dexteritydiff/tests/test_compouddiff.py
collective/dexteritydiff/tests/test_filelistdiff.py
collective/dexteritydiff/tests/test_install.py
docs/HISTORY.txt