Metadata-Version: 1.0
Name: collective.dexteritydiff
Version: 0.1b4
Summary: Provide the DexterityCompoundDiff diff type for Products.CMFEditions, analogous to ATCompoudDiff.
Home-page: http://svn.plone.org/svn/collective/collective.dexteritydiff
Author: Rafael Oliveira
Author-email: rafaelbco@gmail.com
License: GPL
Keywords: plone dexterity
Platform: UNKNOWN
Classifier: Programming Language :: Python
